{
  "$schema": "./node_modules/wrangler/config-schema.json",
  "name": "invencible",
  "main": "./workers/app.ts",
  "compatibility_date": "2025-04-01",
  "compatibility_flags": ["nodejs_compat"],
  "observability": { "enabled": true },
  "upload_source_maps": true,
  "vars": {
    "VALUE_FROM_CLOUDFLARE": "Hello from Cloudflare",
    "NODE_ENV": "production"
  },
  "routes": [
    { "pattern": "imbencible.com/*", "zone_name": "imbencible.com" },
    { "pattern": "www.imbencible.com/*", "zone_name": "imbencible.com" }
  ],
  "workers_dev": true
}
